{
  "name": "debug_log",
  "desc": "Append an entry to the shared debug action log (Downloads/debug_action_log.md). Use during self-debug to track investigation progress.",
  "bridge": "SelfDebug",
  "category": "action",
  "always": false,
  "param_count": 3,
  "parameters": [
    {
      "name": "item_id",
      "type": "string",
      "description": "Item being tracked (e.g., 'B10', 'REQ-1', 'BUG-1')",
      "required": true
    },
    {
      "name": "status",
      "type": "string",
      "description": "Status: investigating, confirmed, fixed, blocked, deferred",
      "required": false
    },
    {
      "name": "detail",
      "type": "string",
      "description": "What was found, done, or decided",
      "required": false
    }
  ],
  "keywords": [
    "debug log",
    "action log",
    "self debug log",
    "track progress"
  ]
}