{
  "class": "CalculationWriteKitchenVentilationCaptureVelocityToKitchenParametersCommand",
  "desc": "",
  "summary": "",
  "usecase": "",
  "notfor": "",
  "precondition": "",
  "postcondition": "",
  "sideeffects": "",
  "logictree": "",
  "keywords": [
    "calculationwritekitchenventilationcapturevelocitytokitchenparameters",
    "write capture velocity kitchen"
  ],
  "intent_patterns": [],
  "pillar": "",
  "pillar_raw": "",
  "selection_inputs": [],
  "config_inputs": [
    {
      "name": "PresetKind",
      "type": "string",
      "description": "Deterministic config preset",
      "default": "\"calculation_defaults\""
    }
  ],
  "outputs": [],
  "related_commands": [],
  "aiprompts": null,
  "has_restapi": false
}